Compiled from "Lalala.java"
public class org.mule.runtime.module.extension.internal.runtime.operation.Lalala implements org.mule.runtime.module.extension.internal.runtime.execution.ByteBuddyWrappedMethodComponentExecutor$MethodComponentExecutorWrapper {
  public java.lang.Object execute(org.mule.runtime.extension.api.runtime.operation.ExecutionContext);
    Code:
       0: aload_0
       1: getfield      #1                  // Field componentInstance:Lorg/mule/runtime/module/extension/internal/runtime/operation/ReflectiveMethodOperationExecutorTestCase$PrimitiveTypesTestOperations;
       4: aload_0
       5: getfield      #2                  // Field charValueResolver:Lorg/mule/runtime/module/extension/internal/runtime/resolver/ArgumentResolver;
       8: aload_1
       9: invokeinterface #3,  2            // InterfaceMethod org/mule/runtime/module/extension/internal/runtime/resolver/ArgumentResolver.resolve:(Lorg/mule/runtime/extension/api/runtime/operation/ExecutionContext;)Ljava/util/function/Supplier;
      14: invokeinterface #4,  1            // InterfaceMethod java/util/function/Supplier.get:()Ljava/lang/Object;
      19: checkcast     #5                  // class java/lang/Character
      22: invokevirtual #6                  // Method java/lang/Character.charValue:()C
      25: aload_0
      26: getfield      #7                  // Field byteValueResolver:Lorg/mule/runtime/module/extension/internal/runtime/resolver/ArgumentResolver;
      29: aload_1
      30: invokeinterface #3,  2            // InterfaceMethod org/mule/runtime/module/extension/internal/runtime/resolver/ArgumentResolver.resolve:(Lorg/mule/runtime/extension/api/runtime/operation/ExecutionContext;)Ljava/util/function/Supplier;
      35: invokeinterface #4,  1            // InterfaceMethod java/util/function/Supplier.get:()Ljava/lang/Object;
      40: checkcast     #8                  // class java/lang/Byte
      43: invokevirtual #9                  // Method java/lang/Byte.byteValue:()B
      46: aload_0
      47: getfield      #10                 // Field shortValueResolver:Lorg/mule/runtime/module/extension/internal/runtime/resolver/ArgumentResolver;
      50: aload_1
      51: invokeinterface #3,  2            // InterfaceMethod org/mule/runtime/module/extension/internal/runtime/resolver/ArgumentResolver.resolve:(Lorg/mule/runtime/extension/api/runtime/operation/ExecutionContext;)Ljava/util/function/Supplier;
      56: invokeinterface #4,  1            // InterfaceMethod java/util/function/Supplier.get:()Ljava/lang/Object;
      61: checkcast     #11                 // class java/lang/Short
      64: invokevirtual #12                 // Method java/lang/Short.shortValue:()S
      67: aload_0
      68: getfield      #13                 // Field intValueResolver:Lorg/mule/runtime/module/extension/internal/runtime/resolver/ArgumentResolver;
      71: aload_1
      72: invokeinterface #3,  2            // InterfaceMethod org/mule/runtime/module/extension/internal/runtime/resolver/ArgumentResolver.resolve:(Lorg/mule/runtime/extension/api/runtime/operation/ExecutionContext;)Ljava/util/function/Supplier;
      77: invokeinterface #4,  1            // InterfaceMethod java/util/function/Supplier.get:()Ljava/lang/Object;
      82: checkcast     #14                 // class java/lang/Integer
      85: invokevirtual #15                 // Method java/lang/Integer.intValue:()I
      88: aload_0
      89: getfield      #16                 // Field longValueResolver:Lorg/mule/runtime/module/extension/internal/runtime/resolver/ArgumentResolver;
      92: aload_1
      93: invokeinterface #3,  2            // InterfaceMethod org/mule/runtime/module/extension/internal/runtime/resolver/ArgumentResolver.resolve:(Lorg/mule/runtime/extension/api/runtime/operation/ExecutionContext;)Ljava/util/function/Supplier;
      98: invokeinterface #4,  1            // InterfaceMethod java/util/function/Supplier.get:()Ljava/lang/Object;
     103: checkcast     #17                 // class java/lang/Long
     106: invokevirtual #18                 // Method java/lang/Long.longValue:()J
     109: aload_0
     110: getfield      #19                 // Field floatValueResolver:Lorg/mule/runtime/module/extension/internal/runtime/resolver/ArgumentResolver;
     113: aload_1
     114: invokeinterface #3,  2            // InterfaceMethod org/mule/runtime/module/extension/internal/runtime/resolver/ArgumentResolver.resolve:(Lorg/mule/runtime/extension/api/runtime/operation/ExecutionContext;)Ljava/util/function/Supplier;
     119: invokeinterface #4,  1            // InterfaceMethod java/util/function/Supplier.get:()Ljava/lang/Object;
     124: checkcast     #20                 // class java/lang/Float
     127: invokevirtual #21                 // Method java/lang/Float.floatValue:()F
     130: aload_0
     131: getfield      #22                 // Field doubleValueResolver:Lorg/mule/runtime/module/extension/internal/runtime/resolver/ArgumentResolver;
     134: aload_1
     135: invokeinterface #3,  2            // InterfaceMethod org/mule/runtime/module/extension/internal/runtime/resolver/ArgumentResolver.resolve:(Lorg/mule/runtime/extension/api/runtime/operation/ExecutionContext;)Ljava/util/function/Supplier;
     140: invokeinterface #4,  1            // InterfaceMethod java/util/function/Supplier.get:()Ljava/lang/Object;
     145: checkcast     #23                 // class java/lang/Double
     148: invokevirtual #24                 // Method java/lang/Double.doubleValue:()D
     151: aload_0
     152: getfield      #25                 // Field booleanValueResolver:Lorg/mule/runtime/module/extension/internal/runtime/resolver/ArgumentResolver;
     155: aload_1
     156: invokeinterface #3,  2            // InterfaceMethod org/mule/runtime/module/extension/internal/runtime/resolver/ArgumentResolver.resolve:(Lorg/mule/runtime/extension/api/runtime/operation/ExecutionContext;)Ljava/util/function/Supplier;
     161: invokeinterface #4,  1            // InterfaceMethod java/util/function/Supplier.get:()Ljava/lang/Object;
     166: checkcast     #26                 // class java/lang/Boolean
     169: invokevirtual #27                 // Method java/lang/Boolean.booleanValue:()Z
     172: invokevirtual #28                 // Method org/mule/runtime/module/extension/internal/runtime/operation/ReflectiveMethodOperationExecutorTestCase$PrimitiveTypesTestOperations.allCombined:(CBSIJFDZ)V
     175: aconst_null
     176: areturn

  public org.mule.runtime.module.extension.internal.runtime.operation.Lalala(org.mule.runtime.module.extension.internal.runtime.operation.ReflectiveMethodOperationExecutorTestCase$PrimitiveTypesTestOperations, org.mule.runtime.module.extension.internal.runtime.resolver.ArgumentResolver<java.lang.Character>, org.mule.runtime.module.extension.internal.runtime.resolver.ArgumentResolver<java.lang.Byte>, org.mule.runtime.module.extension.internal.runtime.resolver.ArgumentResolver<java.lang.Short>, org.mule.runtime.module.extension.internal.runtime.resolver.ArgumentResolver<java.lang.Integer>, org.mule.runtime.module.extension.internal.runtime.resolver.ArgumentResolver<java.lang.Long>, org.mule.runtime.module.extension.internal.runtime.resolver.ArgumentResolver<java.lang.Float>, org.mule.runtime.module.extension.internal.runtime.resolver.ArgumentResolver<java.lang.Double>, org.mule.runtime.module.extension.internal.runtime.resolver.ArgumentResolver<java.lang.Boolean>);
    Code:
       0: aload_0
       1: invokespecial #29                 // Method java/lang/Object."<init>":()V
       4: aload_0
       5: aload_1
       6: putfield      #1                  // Field componentInstance:Lorg/mule/runtime/module/extension/internal/runtime/operation/ReflectiveMethodOperationExecutorTestCase$PrimitiveTypesTestOperations;
       9: aload_0
      10: aload_2
      11: putfield      #2                  // Field charValueResolver:Lorg/mule/runtime/module/extension/internal/runtime/resolver/ArgumentResolver;
      14: aload_0
      15: aload_3
      16: putfield      #7                  // Field byteValueResolver:Lorg/mule/runtime/module/extension/internal/runtime/resolver/ArgumentResolver;
      19: aload_0
      20: aload         4
      22: putfield      #10                 // Field shortValueResolver:Lorg/mule/runtime/module/extension/internal/runtime/resolver/ArgumentResolver;
      25: aload_0
      26: aload         5
      28: putfield      #13                 // Field intValueResolver:Lorg/mule/runtime/module/extension/internal/runtime/resolver/ArgumentResolver;
      31: aload_0
      32: aload         6
      34: putfield      #16                 // Field longValueResolver:Lorg/mule/runtime/module/extension/internal/runtime/resolver/ArgumentResolver;
      37: aload_0
      38: aload         7
      40: putfield      #19                 // Field floatValueResolver:Lorg/mule/runtime/module/extension/internal/runtime/resolver/ArgumentResolver;
      43: aload_0
      44: aload         8
      46: putfield      #22                 // Field doubleValueResolver:Lorg/mule/runtime/module/extension/internal/runtime/resolver/ArgumentResolver;
      49: aload_0
      50: aload         9
      52: putfield      #25                 // Field booleanValueResolver:Lorg/mule/runtime/module/extension/internal/runtime/resolver/ArgumentResolver;
      55: return
}
