Compiled from "SayMyName.java"
public class org.mule.runtime.module.extension.internal.runtime.operation.SayMyName implements org.mule.runtime.module.extension.internal.runtime.execution.ByteBuddyWrappedMethodComponentExecutor$MethodComponentExecutorWrapper {
  public java.lang.Object execute(org.mule.runtime.extension.api.runtime.operation.ExecutionContext);
    Code:
       0: aload_0
       1: getfield      #1                  // Field componentInstance:Lorg/mule/test/heisenberg/extension/HeisenbergOperations;
       4: aload_0
       5: getfield      #2                  // Field configResolver:Lorg/mule/runtime/module/extension/internal/runtime/resolver/ArgumentResolver;
       8: aload_1
       9: invokeinterface #3,  2            // InterfaceMethod org/mule/runtime/module/extension/internal/runtime/resolver/ArgumentResolver.resolve:(Lorg/mule/runtime/extension/api/runtime/operation/ExecutionContext;)Ljava/util/function/Supplier;
      14: invokeinterface #4,  1            // InterfaceMethod java/util/function/Supplier.get:()Ljava/lang/Object;
      19: checkcast     #5                  // class org/mule/test/heisenberg/extension/HeisenbergExtension
      22: invokevirtual #6                  // Method org/mule/test/heisenberg/extension/HeisenbergOperations.sayMyName:(Lorg/mule/test/heisenberg/extension/HeisenbergExtension;)Ljava/lang/String;
      25: areturn

  public org.mule.runtime.module.extension.internal.runtime.operation.SayMyName(org.mule.test.heisenberg.extension.HeisenbergOperations, org.mule.runtime.module.extension.internal.runtime.resolver.ArgumentResolver<org.mule.test.heisenberg.extension.HeisenbergExtension>);
    Code:
       0: aload_0
       1: invokespecial #7                  // Method java/lang/Object."<init>":()V
       4: aload_0
       5: aload_1
       6: putfield      #1                  // Field componentInstance:Lorg/mule/test/heisenberg/extension/HeisenbergOperations;
       9: aload_0
      10: aload_2
      11: putfield      #2                  // Field configResolver:Lorg/mule/runtime/module/extension/internal/runtime/resolver/ArgumentResolver;
      14: return
}
